lump/__init__.py
lump/cache.py
lump/config.py
lump/csv.py
lump/decorators.py
lump/gunicorn.py
lump/helpers.py
lump/http.py
lump/humanreadable.py
lump/keypress.py
lump/multithreading.py
lump/null.py
lump/profiling.py
lump/stream.py
lump-0.1.4.dist-info/LICENSE
lump-0.1.4.dist-info/METADATA
lump-0.1.4.dist-info/WHEEL
lump-0.1.4.dist-info/top_level.txt
lump-0.1.4.dist-info/RECORD
